README.md
setup.py
regim/__init__.py
regim/config.py
regim/data_utils.py
regim/dl_utils.py
regim/event.py
regim/grad_rat_sched.py
regim/metrics.py
regim/pipeline.py
regim/probe.py
regim/tensorboard_probe.py
regim/tensorwatch_probe.py
regim/train_test.py
regim/utils.py
regim/weighted_mse_loss.py
regim.egg-info/PKG-INFO
regim.egg-info/SOURCES.txt
regim.egg-info/dependency_links.txt
regim.egg-info/requires.txt
regim.egg-info/top_level.txt