Metadata-Version: 2.1
Name: regim
Version: 0.8.2
Summary: PyTorch Train Test Regiment Pipeline
Home-page: https://github.com/sytelus/regim
Author: Shital Shah
Author-email: sytelus@gmail.com
License: MIT
Platform: UNKNOWN
Classifier: Programming Language :: Python :: 3
Classifier: License :: OSI Approved :: MIT License
Classifier: Operating System :: OS Independent
